django_tornado/__init__.py
django_tornado/decorators.py
django_tornado/http_client.py
django_tornado/audit.py
django_tornado/management/__init__.py
django_tornado/management/commands/__init__.py
django_tornado/management/commands/run_tornado.py
django_tornado-1.1.4.dist-info/pydist.json
django_tornado-1.1.4.dist-info/WHEEL
django_tornado-1.1.4.dist-info/top_level.txt
django_tornado-1.1.4.dist-info/METADATA
django_tornado-1.1.4.dist-info/DESCRIPTION.rst
django_tornado-1.1.4.dist-info/RECORD
