Metadata-Version: 2.0
Name: django-tornado
Version: 1.1.4
Summary: Django/Tornado integration made easy.
Home-page: UNKNOWN
Author: Jeff Buttars
Author-email: jeffbuttars@gmail.com
License: MIT
Platform: UNKNOWN
Requires-Dist: tornado
Requires-Dist: Django
